open_source_sdk/__init__.py
open_source_sdk/_version.py
open_source_sdk/main.py
open_source_sdk-0.0.3.dist-info/LICENSE
open_source_sdk-0.0.3.dist-info/METADATA
open_source_sdk-0.0.3.dist-info/WHEEL
open_source_sdk-0.0.3.dist-info/top_level.txt
open_source_sdk-0.0.3.dist-info/RECORD
